<?xml version="1.0" encoding="utf-8" ?><dwsync><file name=".gitattributes" server="linux175.unoeuro.com" local="3595319779" remote="3596027100" Dst="-1" /><file name="flow1.pdf" server="linux175.unoeuro.com" local="3588235208" remote="3596566200" Dst="-1" /><file name="flow2.pdf" server="linux175.unoeuro.com" local="3590036532" remote="3596566200" Dst="-1" /><file name="flow3.pdf" server="linux175.unoeuro.com" local="3592473530" remote="3596566200" Dst="-1" /><file name="flow3iphone.xd" server="linux175.unoeuro.com" local="3592812204" remote="3596566200" Dst="-1" /><file name="flow3tablet.xd" server="linux175.unoeuro.com" local="3592472682" remote="3596566200" Dst="-1" /><file name="flow4.pdf" server="linux175.unoeuro.com" local="3596026955" remote="3596566200" Dst="-1" /><file name="index.html" server="linux175.unoeuro.com" local="3596005632" remote="3596027160" Dst="-1" /><file name="portfolioxd.xd" server="linux175.unoeuro.com" local="3588317097" remote="3596566200" Dst="-1" /><file name="projekt1.html" server="linux175.unoeuro.com" local="3596652210" remote="3596653260" Dst="-1" /><file name="projekt2.html" server="linux175.unoeuro.com" local="3596649771" remote="3596653260" Dst="-1" /><file name="projekt3.html" server="linux175.unoeuro.com" local="3596650806" remote="3596653260" Dst="-1" /><file name="projekt4.html" server="linux175.unoeuro.com" local="3596651923" remote="3596653260" Dst="-1" /><file name="projekter.html" server="linux175.unoeuro.com" local="3596641359" remote="3596641440" Dst="-1" /><file name="readme.txt" server="linux175.unoeuro.com" local="3499678988" remote="3596566200" Dst="-1" /><file name="skdslider.css" server="linux175.unoeuro.com" local="3595491097" remote="3596566200" Dst="-1" /><file name="styles.css" server="linux175.unoeuro.com" local="3596722591" remote="3596741220" Dst="-1" /><file name="eksamensprojekt1sem2017.pdf" server="linux175.unoeuro.com" local="3596544374" remote="3596566200" Dst="-1" /><file name="info.html" server="linux175.unoeuro.com" local="3596639740" remote="3596640300" Dst="-1" /><file name="kontakt.html" server="linux175.unoeuro.com" local="3596637134" remote="3596640300" Dst="-1" /><file name="obs_pbs_wbs.pdf" server="linux175.unoeuro.com" local="3596098364" remote="3596566200" Dst="-1" /><file name="programmer.html" server="linux175.unoeuro.com" local="3596639628" remote="3596640300" Dst="-1" /><file name="projekt5.html" server="linux175.unoeuro.com" local="3596740962" remote="3596741220" Dst="-1" /><file name="protoeksamen2017.xd" server="linux175.unoeuro.com" local="3596538603" remote="3596566200" Dst="-1" /><file name="Untitled-1.html" server="linux175.unoeuro.com" local="3596093117" remote="3596566200" Dst="-1" /><file name="flow3rapportremake.pdf" server="linux175.unoeuro.com" local="3596571445" remote="3596640240" Dst="-1" /><file name="læring.html" server="linux175.unoeuro.com" local="3596625263" remote="3596640300" Dst="-1" /><file name="flow1projektbeskrivelse.pdf" server="linux175.unoeuro.com" local="3596643819" remote="3596653260" Dst="-1" /><file name="flow2projektbeskrivelse.pdf" server="linux175.unoeuro.com" local="3596644736" remote="3596653260" Dst="-1" /><file name="flow3projektbeskrivelse.pdf" server="linux175.unoeuro.com" local="3596645324" remote="3596653260" Dst="-1" /><file name="flow4projektbeskrivelse.pdf" server="linux175.unoeuro.com" local="3596650384" remote="3596653260" Dst="-1" /><file name="eksamensrapport2017.pdf" server="linux175.unoeuro.com" local="3596743048" remote="3596743080" Dst="-1" /></dwsync>